whereami/__init__.py
whereami/__init___flymake.py
whereami/__main__.py
whereami/compat.py
whereami/get_data.py
whereami/learn.py
whereami/mobile.py
whereami/pipeline.py
whereami/predict.py
whereami/utils.py
whereami-0.4.90.dist-info/LICENSE
whereami-0.4.90.dist-info/METADATA
whereami-0.4.90.dist-info/WHEEL
whereami-0.4.90.dist-info/entry_points.txt
whereami-0.4.90.dist-info/top_level.txt
whereami-0.4.90.dist-info/RECORD
